Field.py
__init__.py
OskarFieldModule-0.4.3.dist-info/LICENSE
OskarFieldModule-0.4.3.dist-info/METADATA
OskarFieldModule-0.4.3.dist-info/WHEEL
OskarFieldModule-0.4.3.dist-info/top_level.txt
OskarFieldModule-0.4.3.dist-info/RECORD
