Metadata-Version: 2.1
Name: OskarFieldModule
Version: 0.4.3
Summary: Package for calculating electric and magnetic fields and potentials in the FYS-1120 Course 
Author-email: Oskar Idland <oskaridland@hotmail.com>
Project-URL: Homepage, https://github.com/Oskar-Idland/Oskar-Field-Module
Project-URL: Bug Tracker, https://github.com/Oskar-Idland/Oskar-Field-Module/issues
Classifier: Programming Language :: Python :: 3
Classifier: License :: OSI Approved :: MIT License
Classifier: Operating System :: OS Independent
Requires-Python: >=3.7
License-File: LICENSE
